{
    "hip": "pelvis",
    "spine1": "spine_01",
    "spine2": "spine_02",
    "spine3": "spine_03",
    "spine4": "spine_05",
    "neck1": "neck_01",
    "neck2": "neck_02",
    "head": "head",
    "l_shoulder": "clavicle_l",
    "l_upperarm": "upperarm_l",
    "l_forearm": "lowerarm_l",
    "l_forearmtwist1": "lowerarm_twist_01_l",
    "l_forearmtwist2": "lowerarm_twist_02_l",
    "l_hand": "hand_l",
    "l_hand_anchor": "weapon_l",
    "l_thumb1": "thumb_01_l",
    "l_thumb2": "thumb_02_l",
    "l_thumb3": "thumb_03_l",
    "l_indexmetacarpal": "index_metacarpal_l",
    "l_index1": "index_01_l",
    "l_index2": "index_02_l",
    "l_index3": "index_03_l",
    "l_midmetacarpal": "middle_metacarpal_l",
    "l_mid1": "middle_01_l",
    "l_mid2": "middle_02_l",
    "l_mid3": "middle_03_l",
    "l_ringmetacarpal": "ring_metacarpal_l",
    "l_ring1": "ring_01_l",
    "l_ring2": "ring_02_l",
    "l_ring3": "ring_03_l",
    "l_pinkymetacarpal": "pinky_metacarpal_l",
    "l_pinky1": "pinky_01_l",
    "l_pinky2": "pinky_02_l",
    "l_pinky3": "pinky_03_l",
    "l_upperarmtwist1": "upperarm_twist_01_l",
    "l_upperarmtwist2": "upperarm_twist_02_l",
    "r_shoulder": "clavicle_r",
    "r_upperarm": "upperarm_r",
    "r_forearm": "lowerarm_r",
    "r_forearmtwist1": "lowerarm_twist_01_r",
    "r_forearmtwist2": "lowerarm_twist_02_r",
    "r_hand": "hand_r",
    "r_hand_anchor": "weapon_r",
    "r_thumb1": "thumb_01_r",
    "r_thumb2": "thumb_02_r",
    "r_thumb3": "thumb_03_r",
    "r_indexmetacarpal": "index_metacarpal_r",
    "r_index1": "index_01_r",
    "r_index2": "index_02_r",
    "r_index3": "index_03_r",
    "r_midmetacarpal": "middle_metacarpal_r",
    "r_mid1": "middle_01_r",
    "r_mid2": "middle_02_r",
    "r_mid3": "middle_03_r",
    "r_ringmetacarpal": "ring_metacarpal_r",
    "r_ring1": "ring_01_r",
    "r_ring2": "ring_02_r",
    "r_ring3": "ring_03_r",
    "r_pinkymetacarpal": "pinky_metacarpal_r",
    "r_pinky1": "pinky_01_r",
    "r_pinky2": "pinky_02_r",
    "r_pinky3": "pinky_03_r",
    "r_upperarmtwist1": "upperarm_twist_01_r",
    "r_upperarmtwist2": "upperarm_twist_02_r",
    "r_thigh": "thigh_r",
    "r_shin": "calf_r",
    "r_foot": "foot_r",
    "r_toes": "ball_r",
    "r_bigtoe1": "bigtoe_01_r",
    "r_bigtoe2": "bigtoe_02_r",
    "r_indextoe1": "indextoe_01_r",
    "r_indextoe2": "indextoe_02_r",
    "r_midtoe1": "middletoe_01_r",
    "r_midtoe2": "middletoe_02_r",
    "r_ringtoe1": "ringtoe_01_r",
    "r_ringtoe2": "ringtoe_02_r",
    "r_pinkytoe1": "littletoe_01_r",
    "r_pinkytoe2": "littletoe_02_r",
    "r_metatarsal": "metatarsal_r",
    "r_thightwist1": "thigh_twist_01_r",
    "r_thightwist2": "thigh_twist_02_r",
    "l_thigh": "thigh_l",
    "l_shin": "calf_l",
    "l_foot": "foot_l",
    "l_toes": "ball_l",
    "l_bigtoe1": "bigtoe_01_l",
    "l_bigtoe2": "bigtoe_02_l",
    "l_indextoe1": "indextoe_01_l",
    "l_indextoe2": "indextoe_02_l",
    "l_midtoe1": "middletoe_01_l",
    "l_midtoe2": "middletoe_02_l",
    "l_ringtoe1": "ringtoe_01_l",
    "l_ringtoe2": "ringtoe_02_l",
    "l_pinkytoe1": "littletoe_01_l",
    "l_pinkytoe2": "littletoe_02_l",
    "l_metatarsal": "metatarsal_l",
    "l_thightwist1": "thigh_twist_01_l",
    "l_thightwist2": "thigh_twist_02_l",
    "lowerjaw": "FACIAL_C_Jaw",
    "chin": "FACIAL_C_Chin",
    "lowerteeth": "FACIAL_C_TeethLower",
    "upperteeth": "FACIAL_C_TeethUpper",
    "l_eye": "FACIAL_L_Eye",
    "r_eye": "FACIAL_R_Eye",
    "l_ear": "FACIAL_L_Ear",
    "r_ear": "FACIAL_R_Ear",
    "tongue01": "FACIAL_C_Tongue1",
    "tongue03": "FACIAL_C_Tongue2",
    "tongue05": "FACIAL_C_Tongue3",
    "lipuppermiddle": "FACIAL_C_LipUpper",
    "liplowermiddle": "FACIAL_C_LipLower",
    "l_lipcorner": "FACIAL_L_LipCorner",
    "l_liplower": "FACIAL_L_LipLower",
    "r_liplower": "FACIAL_R_LipLower",
    "r_lipcorner": "FACIAL_R_LipCorner",
    "l_lipupper": "FACIAL_L_LipUpper",
    "r_lipupper": "FACIAL_R_LipUpper",
    "l_eyelidupper": "FACIAL_L_EyelidUpperA",
    "l_eyelidlower": "FACIAL_L_EyelidLowerA",
    "r_eyelidupper": "FACIAL_R_EyelidUpperA",
    "r_eyelidlower": "FACIAL_R_EyelidLowerA",
    "l_cheeklower": "FACIAL_L_CheekLower",
    "r_cheeklower": "FACIAL_R_CheekLower",
    "l_cheek": "FACIAL_L_CheekOuter",
    "r_cheek": "FACIAL_R_CheekOuter",   
    "l_nostril": "FACIAL_L_Nostril",
    "r_nostril": "FACIAL_R_Nostril",
    "centerbrow": "FACIAL_C_Forehead",
    "l_browinner": "FACIAL_L_ForeheadIn",
    "l_browouter": "FACIAL_L_ForeheadOut",
    "r_browinner": "FACIAL_R_ForeheadIn",
    "r_browouter": "FACIAL_R_ForeheadOut",
    "l_squint": "FACIAL_L_EyesackLower",
    "r_squint": "FACIAL_R_EyesackLower",
    "l_infraorbital": "FACIAL_L_CheekInner",
    "r_infraorbital": "FACIAL_R_CheekInner",
    "lowerfacerig": "lowerfacerig",
    "upperfacerig": "upperfacerig",
    "l_pectoral": "pectoral_l",
    "r_pectoral": "pectoral_r"
}